constants.py
grepme.py
login.py
grepme/__init__.py
grepme/__main__.py
grepme/constants.py
grepme/grepme.py
grepme/http.py
grepme/lib.py
grepme/login.py
grepme-1.4.0.dist-info/LICENSE
grepme-1.4.0.dist-info/METADATA
grepme-1.4.0.dist-info/WHEEL
grepme-1.4.0.dist-info/entry_points.txt
grepme-1.4.0.dist-info/top_level.txt
grepme-1.4.0.dist-info/RECORD
