Metadata-Version: 2.1
Name: grepme
Version: 1.4.0
Summary: grep for GroupMe
Home-page: https://github.com/jyn514/grepme
Author: Joshua Nelson
Author-email: jyn514@gmail.com
License: BSD
Keywords: grep search chat web groupme
Platform: UNKNOWN
Classifier: Development Status :: 4 - Beta
Classifier: Environment :: Console
Classifier: Intended Audience :: End Users/Desktop
Classifier: Intended Audience :: Developers
Classifier: Intended Audience :: System Administrators
Classifier: Programming Language :: Python :: 2
Classifier: Programming Language :: Python :: 2.7
Classifier: Programming Language :: Python :: 3
Classifier: License :: OSI Approved :: BSD License
Classifier: Operating System :: OS Independent
Classifier: Topic :: Communications :: Chat
Requires-Dist: requests
Requires-Dist: keyring
Requires-Dist: diskcache
Requires-Dist: configparse ; python_version>='3'
